warp/__init__.py
warp/bin/darwin/isoltest
warp/bin/darwin/nethersolc
warp/bin/linux/isoltest
warp/bin/linux/nethersolc
warp/cairo-src/.isort.cfg
warp/cairo-src/evm/array.cairo
warp/cairo-src/evm/bit_packing.cairo
warp/cairo-src/evm/calls.cairo
warp/cairo-src/evm/exec_env.cairo
warp/cairo-src/evm/hashing.cairo
warp/cairo-src/evm/memory.cairo
warp/cairo-src/evm/pow2.cairo
warp/cairo-src/evm/uint256.cairo
warp/cairo-src/evm/utils.cairo
warp/cairo-src/evm/yul_api.cairo
warp/cli/__init__.py
warp/cli/cli.py
warp/cli/commands.py
warp/cli/encoding.py
warp/nethersolc.py
warp/test_tool/__init__.py
warp/test_tool/example/contracts/arrays_complex_from_and_to_storage.sol
warp/test_tool/example/contracts/modifier_loop.sol
warp/test_tool/warp_test.py
warp/yul/AstMapper.py
warp/yul/AstTools.py
warp/yul/AstVisitor.py
warp/yul/BuiltinHandler.py
warp/yul/ConstantFolder.py
warp/yul/DeadcodeEliminator.py
warp/yul/ExpressionSplitter.py
warp/yul/FoldIf.py
warp/yul/ForLoopEliminator.py
warp/yul/ForLoopSimplifier.py
warp/yul/FunctionGenerator.py
warp/yul/FunctionPruner.py
warp/yul/Imports.py
warp/yul/LeaveNormalizer.py
warp/yul/NameGenerator.py
warp/yul/Renamer.py
warp/yul/RevertNormalizer.py
warp/yul/Scope.py
warp/yul/ScopeFlattener.py
warp/yul/SwitchToIfVisitor.py
warp/yul/ToCairoVisitor.py
warp/yul/VariableInliner.py
warp/yul/WarpException.py
warp/yul/__init__.py
warp/yul/ast.py
warp/yul/call_graph.py
warp/yul/extract_block.py
warp/yul/implicits.py
warp/yul/main.py
warp/yul/parse.py
warp/yul/parse_object.py
warp/yul/starknet_utils.py
warp/yul/storage_access.py
warp/yul/top_sort.py
warp/yul/utils.py
sol_warp-1.2.0.dist-info/entry_points.txt
sol_warp-1.2.0.dist-info/LICENSE
sol_warp-1.2.0.dist-info/WHEEL
sol_warp-1.2.0.dist-info/METADATA
sol_warp-1.2.0.dist-info/RECORD
