Metadata-Version: 2.1
Name: sol-warp
Version: 1.2.0
Summary: A Solidity to Cairo Transpiler
Home-page: https://github.com/NethermindEth/warp
License: Apache 2.0
Keywords: Ethereum,Layer2,ETH,StarkNet,Nethermind,StarkWare,transpilation,warp,transpiler,cairo
Author: Nethermind
Author-email: hello@nethermind.io
Requires-Python: >=3.7,<3.10
Classifier: License :: OSI Approved :: Apache Software License
Classifier: License :: Other/Proprietary License
Classifier: Programming Language :: Python :: 3
Classifier: Programming Language :: Python :: 3.7
Classifier: Programming Language :: Python :: 3.8
Classifier: Programming Language :: Python :: 3.9
Requires-Dist: black (==22.1.0)
Requires-Dist: cairo-lang (==0.7.0)
Requires-Dist: click
Requires-Dist: eth-abi
Requires-Dist: importlib_resources
Requires-Dist: pytest
Requires-Dist: pytest-check
Requires-Dist: pytest-xdist (>=2.5.0,<3.0.0)
Requires-Dist: web3 (>=5.12)
Project-URL: Repository, https://github.com/NethermindEth/warp
